msclap/CLAPWrapper.py
msclap/__init__.py
msclap/configs/config_2022.yml
msclap/configs/config_2023.yml
msclap/configs/config_clapcap.yml
msclap/models/__init__.py
msclap/models/audio.py
msclap/models/clap.py
msclap/models/config.py
msclap/models/htsat.py
msclap/models/mapper.py
msclap/models/pytorch_utils.py
msclap/models/utils.py
msclap-1.3.4.dist-info/LICENSE
msclap-1.3.4.dist-info/METADATA
msclap-1.3.4.dist-info/WHEEL
msclap-1.3.4.dist-info/RECORD
