Metadata-Version: 2.3
Name: msclap
Version: 1.3.4
Summary: CLAP (Contrastive Language-Audio Pretraining) is a model that learns acoustic concepts from natural language supervision and enables “Zero-Shot” inference. The model has been extensively evaluated in 26 audio downstream tasks achieving SoTA in several of them including classification, retrieval, and captioning.
License: MIT
Author: Benjamin Elizalde
Requires-Python: >=3.8,<4.0
Classifier: License :: OSI Approved :: MIT License
Classifier: Programming Language :: Python :: 3
Classifier: Programming Language :: Python :: 3.8
Classifier: Programming Language :: Python :: 3.9
Classifier: Programming Language :: Python :: 3.10
Classifier: Programming Language :: Python :: 3.11
Classifier: Programming Language :: Python :: 3.12
Classifier: Programming Language :: Python :: 3.13
Requires-Dist: librosa (>=0.10.1,<0.11.0)
Requires-Dist: numpy (>=1.23.0,<2.0.0)
Requires-Dist: pandas (>=2.0.0,<3.0.0)
Requires-Dist: pyyaml (>=6.0.1,<7.0.0)
Requires-Dist: scikit-learn (>=1.3.1,<2.0.0)
Requires-Dist: torch (>=2.1.0,<3.0.0)
Requires-Dist: torchaudio (>=2.1.0,<3.0.0)
Requires-Dist: torchlibrosa (>=0.1.0,<0.2.0)
Requires-Dist: tqdm (>=4.66.1,<5.0.0)
Requires-Dist: transformers (>=4.34.0,<5.0.0)
